snakemake_storage_plugin_pelican/__init__.py
snakemake_storage_plugin_pelican-0.1.1.dist-info/METADATA
snakemake_storage_plugin_pelican-0.1.1.dist-info/WHEEL
snakemake_storage_plugin_pelican-0.1.1.dist-info/licenses/LICENSE
snakemake_storage_plugin_pelican-0.1.1.dist-info/RECORD
