Metadata-Version: 2.4
Name: snakemake-storage-plugin-pelican
Version: 0.1.1
Summary: A Snakemake Storage Plugin for Pelican Federations
License-File: LICENSE
Author: Justin Hiemstra
Author-email: jhiemstra@wisc.edu
Requires-Python: >=3.12,<4.0
Classifier: Programming Language :: Python :: 3
Classifier: Programming Language :: Python :: 3.12
Classifier: Programming Language :: Python :: 3.13
Classifier: Programming Language :: Python :: 3.14
Requires-Dist: pelicanfs (>=1.2.3)
Requires-Dist: snakemake-interface-common (>=1.21.0,<2.0.0)
Requires-Dist: snakemake-interface-storage-plugins (>=4.2.1,<5.0.0)
